otsunotificationfrequency/__init__.py
otsunotificationfrequency/validator.py
otsunotificationfrequency-2022.11.30.dist-info/LICENSE
otsunotificationfrequency-2022.11.30.dist-info/METADATA
otsunotificationfrequency-2022.11.30.dist-info/WHEEL
otsunotificationfrequency-2022.11.30.dist-info/top_level.txt
otsunotificationfrequency-2022.11.30.dist-info/RECORD
