Metadata-Version: 2.1
Name: otsunotificationfrequency
Version: 2022.11.30
Summary: 要素数が確定されたシーケンスの途中で処理を挟むタイミングの判定を補助します。
Home-page: https://github.com/Otsuhachi/NotificationFrequency
Author: Otsuhachi
Author-email: agequodagis.tufuiegoeris@gmail.com
License: MIT License
Keywords: Python Notification Frequency
License-File: LICENSE
